LICENSE
cblack/__init__.py
cblack/__main__.py
cblack/config/__init__.py
cblack/config/base.py
cblack/config/ini.py
cblack/config/pyprojecttoml.py
cblack/config/setupcfg.py
cblack/config/tox.py
cblack/runner.py
cblack/utils/__init__.py
cblack/utils/files.py
cblack/utils/ini.py
cblack/utils/out.py
cblack/utils/proc.py
configparser_black-0.2.0.dist-info/entry_points.txt
configparser_black-0.2.0.dist-info/LICENSE
configparser_black-0.2.0.dist-info/WHEEL
configparser_black-0.2.0.dist-info/METADATA
configparser_black-0.2.0.dist-info/RECORD
