Metadata-Version: 2.1
Name: configparser-black
Version: 0.2.0
Summary: A wrapper for black to connect with other python configuration files such as setup.cfg and tox.ini
Home-page: https://github.com/tchar/configparser-black
License: MIT
Keywords: black,lint,config,configuration,setup.cfg,tox.ini
Author: tchar
Requires-Python: >=3.6.2
Classifier: Environment :: Console
Classifier: Environment :: Plugins
Classifier: Intended Audience :: Developers
Classifier: License :: OSI Approved :: MIT License
Classifier: Operating System :: OS Independent
Classifier: Operating System :: POSIX
Classifier: Programming Language :: Python :: 3
Classifier: Programming Language :: Python :: 3.6
Classifier: Programming Language :: Python :: 3.7
Classifier: Programming Language :: Python :: 3.8
Classifier: Programming Language :: Python :: 3.9
Classifier: Topic :: Software Development
Classifier: Topic :: Software Development :: Libraries :: Python Modules
Classifier: Topic :: Software Development :: Quality Assurance
Project-URL: Repository, https://github.com/tchar/configparser-black
